staffingetl/__init__.py
staffingetl/doctools.py
staffingetl/indextools.py
staffingetl-0.0.2.dist-info/LICENSE.txt
staffingetl-0.0.2.dist-info/METADATA
staffingetl-0.0.2.dist-info/WHEEL
staffingetl-0.0.2.dist-info/top_level.txt
staffingetl-0.0.2.dist-info/RECORD
